AUTHORS
COPYING
MANIFEST.in
README
setup.py
simplemediawiki.py
docs/conf.py
docs/index.rst
docs/_static/.gitignore
docs/_templates/.gitignore
simplemediawiki.egg-info/PKG-INFO
simplemediawiki.egg-info/SOURCES.txt
simplemediawiki.egg-info/dependency_links.txt
simplemediawiki.egg-info/requires.txt
simplemediawiki.egg-info/top_level.txt