Metadata-Version: 1.1
Name: simplemediawiki
Version: 1.2.0b2
Summary: Extremely low-level wrapper to the MediaWiki API
Home-page: https://github.com/ianweller/python-simplemediawiki
Author: Ian Weller
Author-email: iweller@redhat.com
License: UNKNOWN
Platform: UNKNOWN
Classifier: Programming Language :: Python :: 2
Classifier: Programming Language :: Python :: 3
Classifier: Development Status :: 5 - Production/Stable
Classifier: Intended Audience :: Developers
Classifier: License :: OSI Approved :: GNU Library or Lesser General Public License (LGPL)
